ctools/__init__.py
ctools/main.py
ctools/cmd/__init__.py
ctools/cmd/unpack.py
cjlpytoolkit-1.0.0.dist-info/METADATA
cjlpytoolkit-1.0.0.dist-info/WHEEL
cjlpytoolkit-1.0.0.dist-info/entry_points.txt
cjlpytoolkit-1.0.0.dist-info/top_level.txt
cjlpytoolkit-1.0.0.dist-info/RECORD
