Metadata-Version: 2.1
Name: cjlpytoolkit
Version: 1.0.0
Summary: 常用Python工具库或脚本命令
Home-page: https://www.cjlmonster.cn
Author: cjlmonster
Author-email: cjlmonster@163.com
License: UNKNOWN
Platform: python3
Requires-Python: >=3
